hentailib/__init__.py
hentailib/core.py
hentailib/logger.py
hentailib-1.0.1.dist-info/licenses/LICENSE
hentailib-1.0.1.dist-info/METADATA
hentailib-1.0.1.dist-info/WHEEL
hentailib-1.0.1.dist-info/top_level.txt
hentailib-1.0.1.dist-info/RECORD
