Metadata-Version: 2.4
Name: hentailib
Version: 1.0.1
Summary: Library for easy requests hentai sites
Author-email: Onii-Chan <skobochki.ad@mail.ru>
License: MIT
Project-URL: Repository, https://github.com/SerJo2/hentailib
Project-URL: Issues, https://github.com/SerJo2/hentailib/issues
Project-URL: Changelog, https://github.com/SerJo2/hentailib/blob/master/CHANGELOG.md
Keywords: hentai,requests,rule34
Classifier: Development Status :: 5 - Production/Stable
Classifier: Intended Audience :: Developers
Classifier: Intended Audience :: Information Technology
Classifier: Intended Audience :: Other Audience
Classifier: Topic :: Internet
Classifier: Topic :: Multimedia
Classifier: Programming Language :: Python :: 3
Classifier: Programming Language :: Python :: 3.9
Classifier: Programming Language :: Python :: 3.10
Classifier: Programming Language :: Python :: 3.11
Classifier: Programming Language :: Python :: 3.12
Requires-Python: >=3.9
License-File: LICENSE
Requires-Dist: requests>=2.32.5
Provides-Extra: test
Requires-Dist: pytest>=6.0; extra == "test"
Dynamic: license-file
